{
    "shoulder_pan": {
        "id": 1,
        "drive_mode": 0,
        "homing_offset": 1470,
        "range_min": 713,
        "range_max": 3437
    },
    "shoulder_lift": {
        "id": 2,
        "drive_mode": 0,
        "homing_offset": 1802,
        "range_min": 850,
        "range_max": 3261
    },
    "elbow_flex": {
        "id": 3,
        "drive_mode": 0,
        "homing_offset": 741,
        "range_min": 907,
        "range_max": 3136
    },
    "wrist_flex": {
        "id": 4,
        "drive_mode": 0,
        "homing_offset": -1760,
        "range_min": 807,
        "range_max": 3162
    },
    "wrist_roll": {
        "id": 5,
        "drive_mode": 0,
        "homing_offset": 1893,
        "range_min": 0,
        "range_max": 4095
    },
    "gripper": {
        "id": 6,
        "drive_mode": 0,
        "homing_offset": 1409,
        "range_min": 1709,
        "range_max": 3098
    }
}